Metadata-Version: 2.1
Name: az2py
Version: 0.0.1.1.0
Summary: A very basic calculator
Home-page: UNKNOWN
Author: Rostami
Author-email: MHRo.R84@gmail.com
License: MIT
Keywords: AZPY
Platform: UNKNOWN
Classifier: Development Status :: 5 - Production/Stable
Classifier: Intended Audience :: Education
Classifier: Operating System :: Microsoft :: Windows :: Windows 10
Classifier: License :: OSI Approved :: MIT License
Classifier: Programming Language :: Python :: 3
License-File: LICENCE.txt
